LICENSE
README.md
setup.py
failure_directions/__init__.py
failure_directions/cifar100_run_stable_diffusion_checker.py
failure_directions/cifar10_caption_level.py
failure_directions/cifar10_caption_level_finetune.py
failure_directions/cifar10_run_stable_diffusion_checker.py
failure_directions/ffcv_main.py
failure_directions/train_svms.py
failure_directions.egg-info/PKG-INFO
failure_directions.egg-info/SOURCES.txt
failure_directions.egg-info/dependency_links.txt
failure_directions.egg-info/requires.txt
failure_directions.egg-info/top_level.txt
failure_directions/src/__init__.py
failure_directions/src/cifar_resnet.py
failure_directions/src/clip_utils.py
failure_directions/src/config_parsing.py
failure_directions/src/decoders_and_transforms.py
failure_directions/src/dist_shift_utils.py
failure_directions/src/ds_utils.py
failure_directions/src/ffcv_utils.py
failure_directions/src/imagenet_class_index.py
failure_directions/src/label_maps.py
failure_directions/src/model_utils.py
failure_directions/src/optimizers.py
failure_directions/src/pytorch_datasets.py
failure_directions/src/stable_diffusion_utils.py
failure_directions/src/svm_utils.py
failure_directions/src/trainer.py
failure_directions/src/trainer_latents.py
failure_directions/src/visualization_utils.py
failure_directions/src/wrappers.py