Metadata-Version: 2.1
Name: failure-directions
Version: 0.1.3
Summary: Failure Directions
Home-page: https://github.com/MadryLab/failure-directions
Author: MadryLab
Author-email: saachij@mit.edu
License: MIT
License-File: LICENSE
